{
  "interpretation_id": "2261d015-d687-4fd0-a805-fe91a0ae187f",
  "timestamp": "2025-08-06T11:54:39.764818",
  "patient_id": "1",
  "provider_id": "1",
  "editable": true,
  "finalized": false,
  "summary": {
    "metrics": {
      "mean_glucose": 208.07,
      "std_glucose": 121.5,
      "cv": 58.39,
      "gmi": 8.29,
      "tir_percent": 21.06,
      "below_70_percent": 22.11,
      "below_54_percent": 16.55,
      "above_180_percent": 56.83,
      "above_250_percent": 47.45,
      "tir_count": 182,
      "below_70_count": 191,
      "below_54_count": 143,
      "above_180_count": 491,
      "above_250_count": 410,
      "total_points": 864
    },
    "patterns": {
      "hypoglycemia_events": [
        {
          "timestamp": "2025-08-01T08:00:00+00:00",
          "glucose": 52.0
        },
        {
          "timestamp": "2025-08-01T08:05:00+00:00",
          "glucose": 33.0
        },
        {
          "timestamp": "2025-08-01T08:10:00+00:00",
          "glucose": 49.0
        },
        {
          "timestamp": "2025-08-01T08:15:00+00:00",
          "glucose": 45.0
        },
        {
          "timestamp": "2025-08-01T08:20:00+00:00",
          "glucose": 62.0
        },
        {
          "timestamp": "2025-08-01T08:25:00+00:00",
          "glucose": 61.0
        },
        {
          "timestamp": "2025-08-01T08:30:00+00:00",
          "glucose": 60.0
        },
        {
          "timestamp": "2025-08-01T08:35:00+00:00",
          "glucose": 49.0
        },
        {
          "timestamp": "2025-08-01T08:40:00+00:00",
          "glucose": 32.0
        },
        {
          "timestamp": "2025-08-01T08:45:00+00:00",
          "glucose": 37.0
        },
        {
          "timestamp": "2025-08-01T08:50:00+00:00",
          "glucose": 45.0
        },
        {
          "timestamp": "2025-08-01T08:55:00+00:00",
          "glucose": 53.0
        },
        {
          "timestamp": "2025-08-01T09:00:00+00:00",
          "glucose": 34.0
        },
        {
          "timestamp": "2025-08-01T09:05:00+00:00",
          "glucose": 42.0
        },
        {
          "timestamp": "2025-08-01T09:10:00+00:00",
          "glucose": 30.0
        },
        {
          "timestamp": "2025-08-01T09:15:00+00:00",
          "glucose": 30.0
        },
        {
          "timestamp": "2025-08-01T09:20:00+00:00",
          "glucose": 43.0
        },
        {
          "timestamp": "2025-08-01T09:25:00+00:00",
          "glucose": 48.0
        },
        {
          "timestamp": "2025-08-01T09:30:00+00:00",
          "glucose": 50.0
        },
        {
          "timestamp": "2025-08-01T09:35:00+00:00",
          "glucose": 65.0
        },
        {
          "timestamp": "2025-08-01T12:00:00+00:00",
          "glucose": 55.0
        },
        {
          "timestamp": "2025-08-01T12:05:00+00:00",
          "glucose": 49.0
        },
        {
          "timestamp": "2025-08-01T12:10:00+00:00",
          "glucose": 58.0
        },
        {
          "timestamp": "2025-08-01T12:40:00+00:00",
          "glucose": 69.0
        },
        {
          "timestamp": "2025-08-01T20:00:00+00:00",
          "glucose": 45.0
        },
        {
          "timestamp": "2025-08-01T20:05:00+00:00",
          "glucose": 53.0
        },
        {
          "timestamp": "2025-08-01T20:10:00+00:00",
          "glucose": 57.0
        },
        {
          "timestamp": "2025-08-01T20:15:00+00:00",
          "glucose": 47.0
        },
        {
          "timestamp": "2025-08-01T20:20:00+00:00",
          "glucose": 45.0
        },
        {
          "timestamp": "2025-08-01T20:25:00+00:00",
          "glucose": 32.0
        },
        {
          "timestamp": "2025-08-01T20:30:00+00:00",
          "glucose": 48.0
        },
        {
          "timestamp": "2025-08-01T20:35:00+00:00",
          "glucose": 57.0
        },
        {
          "timestamp": "2025-08-01T20:40:00+00:00",
          "glucose": 42.0
        },
        {
          "timestamp": "2025-08-01T20:45:00+00:00",
          "glucose": 42.0
        },
        {
          "timestamp": "2025-08-01T20:50:00+00:00",
          "glucose": 46.0
        },
        {
          "timestamp": "2025-08-01T20:55:00+00:00",
          "glucose": 38.0
        },
        {
          "timestamp": "2025-08-01T21:00:00+00:00",
          "glucose": 36.0
        },
        {
          "timestamp": "2025-08-01T21:05:00+00:00",
          "glucose": 45.0
        },
        {
          "timestamp": "2025-08-01T21:10:00+00:00",
          "glucose": 30.0
        },
        {
          "timestamp": "2025-08-01T21:15:00+00:00",
          "glucose": 30.0
        },
        {
          "timestamp": "2025-08-01T21:20:00+00:00",
          "glucose": 30.0
        },
        {
          "timestamp": "2025-08-01T21:25:00+00:00",
          "glucose": 48.0
        },
        {
          "timestamp": "2025-08-01T21:30:00+00:00",
          "glucose": 63.0
        },
        {
          "timestamp": "2025-08-01T23:45:00+00:00",
          "glucose": 66.0
        },
        {
          "timestamp": "2025-08-02T08:00:00+00:00",
          "glucose": 48.0
        },
        {
          "timestamp": "2025-08-02T08:05:00+00:00",
          "glucose": 48.0
        },
        {
          "timestamp": "2025-08-02T08:10:00+00:00",
          "glucose": 62.0
        },
        {
          "timestamp": "2025-08-02T08:25:00+00:00",
          "glucose": 63.0
        },
        {
          "timestamp": "2025-08-02T08:30:00+00:00",
          "glucose": 53.0
        },
        {
          "timestamp": "2025-08-02T08:35:00+00:00",
          "glucose": 34.0
        },
        {
          "timestamp": "2025-08-02T08:40:00+00:00",
          "glucose": 41.0
        },
        {
          "timestamp": "2025-08-02T08:45:00+00:00",
          "glucose": 30.0
        },
        {
          "timestamp": "2025-08-02T08:50:00+00:00",
          "glucose": 30.0
        },
        {
          "timestamp": "2025-08-02T08:55:00+00:00",
          "glucose": 48.0
        },
        {
          "timestamp": "2025-08-02T09:00:00+00:00",
          "glucose": 43.0
        },
        {
          "timestamp": "2025-08-02T09:05:00+00:00",
          "glucose": 56.0
        },
        {
          "timestamp": "2025-08-02T09:10:00+00:00",
          "glucose": 48.0
        },
        {
          "timestamp": "2025-08-02T09:15:00+00:00",
          "glucose": 30.0
        },
        {
          "timestamp": "2025-08-02T09:20:00+00:00",
          "glucose": 30.0
        },
        {
          "timestamp": "2025-08-02T09:25:00+00:00",
          "glucose": 30.0
        },
        {
          "timestamp": "2025-08-02T09:30:00+00:00",
          "glucose": 30.0
        },
        {
          "timestamp": "2025-08-02T09:35:00+00:00",
          "glucose": 30.0
        },
        {
          "timestamp": "2025-08-02T09:40:00+00:00",
          "glucose": 30.0
        },
        {
          "timestamp": "2025-08-02T09:45:00+00:00",
          "glucose": 50.0
        },
        {
          "timestamp": "2025-08-02T09:50:00+00:00",
          "glucose": 31.0
        },
        {
          "timestamp": "2025-08-02T09:55:00+00:00",
          "glucose": 40.0
        },
        {
          "timestamp": "2025-08-02T10:00:00+00:00",
          "glucose": 58.0
        },
        {
          "timestamp": "2025-08-02T10:05:00+00:00",
          "glucose": 51.0
        },
        {
          "timestamp": "2025-08-02T10:10:00+00:00",
          "glucose": 45.0
        },
        {
          "timestamp": "2025-08-02T10:15:00+00:00",
          "glucose": 30.0
        },
        {
          "timestamp": "2025-08-02T10:20:00+00:00",
          "glucose": 30.0
        },
        {
          "timestamp": "2025-08-02T10:25:00+00:00",
          "glucose": 46.0
        },
        {
          "timestamp": "2025-08-02T10:30:00+00:00",
          "glucose": 57.0
        },
        {
          "timestamp": "2025-08-02T10:45:00+00:00",
          "glucose": 59.0
        },
        {
          "timestamp": "2025-08-02T10:55:00+00:00",
          "glucose": 67.0
        },
        {
          "timestamp": "2025-08-02T11:00:00+00:00",
          "glucose": 60.0
        },
        {
          "timestamp": "2025-08-02T11:05:00+00:00",
          "glucose": 40.0
        },
        {
          "timestamp": "2025-08-02T11:10:00+00:00",
          "glucose": 58.0
        },
        {
          "timestamp": "2025-08-02T11:15:00+00:00",
          "glucose": 69.0
        },
        {
          "timestamp": "2025-08-02T11:20:00+00:00",
          "glucose": 49.0
        },
        {
          "timestamp": "2025-08-02T11:25:00+00:00",
          "glucose": 65.0
        },
        {
          "timestamp": "2025-08-02T11:30:00+00:00",
          "glucose": 50.0
        },
        {
          "timestamp": "2025-08-02T11:35:00+00:00",
          "glucose": 38.0
        },
        {
          "timestamp": "2025-08-02T11:40:00+00:00",
          "glucose": 40.0
        },
        {
          "timestamp": "2025-08-02T11:45:00+00:00",
          "glucose": 35.0
        },
        {
          "timestamp": "2025-08-02T11:50:00+00:00",
          "glucose": 30.0
        },
        {
          "timestamp": "2025-08-02T11:55:00+00:00",
          "glucose": 43.0
        },
        {
          "timestamp": "2025-08-02T12:00:00+00:00",
          "glucose": 48.0
        },
        {
          "timestamp": "2025-08-02T12:05:00+00:00",
          "glucose": 34.0
        },
        {
          "timestamp": "2025-08-02T12:10:00+00:00",
          "glucose": 43.0
        },
        {
          "timestamp": "2025-08-02T12:15:00+00:00",
          "glucose": 43.0
        },
        {
          "timestamp": "2025-08-02T12:20:00+00:00",
          "glucose": 47.0
        },
        {
          "timestamp": "2025-08-02T12:25:00+00:00",
          "glucose": 36.0
        },
        {
          "timestamp": "2025-08-02T12:30:00+00:00",
          "glucose": 30.0
        },
        {
          "timestamp": "2025-08-02T12:35:00+00:00",
          "glucose": 49.0
        },
        {
          "timestamp": "2025-08-02T12:40:00+00:00",
          "glucose": 37.0
        },
        {
          "timestamp": "2025-08-02T12:45:00+00:00",
          "glucose": 30.0
        },
        {
          "timestamp": "2025-08-02T12:50:00+00:00",
          "glucose": 37.0
        },
        {
          "timestamp": "2025-08-02T12:55:00+00:00",
          "glucose": 38.0
        },
        {
          "timestamp": "2025-08-02T13:00:00+00:00",
          "glucose": 30.0
        },
        {
          "timestamp": "2025-08-02T13:05:00+00:00",
          "glucose": 47.0
        },
        {
          "timestamp": "2025-08-02T13:10:00+00:00",
          "glucose": 35.0
        },
        {
          "timestamp": "2025-08-02T13:15:00+00:00",
          "glucose": 51.0
        },
        {
          "timestamp": "2025-08-02T13:20:00+00:00",
          "glucose": 63.0
        },
        {
          "timestamp": "2025-08-02T13:25:00+00:00",
          "glucose": 63.0
        },
        {
          "timestamp": "2025-08-02T13:40:00+00:00",
          "glucose": 62.0
        },
        {
          "timestamp": "2025-08-02T13:45:00+00:00",
          "glucose": 43.0
        },
        {
          "timestamp": "2025-08-02T13:50:00+00:00",
          "glucose": 32.0
        },
        {
          "timestamp": "2025-08-02T13:55:00+00:00",
          "glucose": 52.0
        },
        {
          "timestamp": "2025-08-02T14:00:00+00:00",
          "glucose": 41.0
        },
        {
          "timestamp": "2025-08-02T14:05:00+00:00",
          "glucose": 54.0
        },
        {
          "timestamp": "2025-08-02T14:10:00+00:00",
          "glucose": 67.0
        },
        {
          "timestamp": "2025-08-02T14:15:00+00:00",
          "glucose": 55.0
        },
        {
          "timestamp": "2025-08-02T14:20:00+00:00",
          "glucose": 67.0
        },
        {
          "timestamp": "2025-08-03T00:00:00+00:00",
          "glucose": 40.0
        },
        {
          "timestamp": "2025-08-03T00:05:00+00:00",
          "glucose": 60.0
        },
        {
          "timestamp": "2025-08-03T00:25:00+00:00",
          "glucose": 61.0
        },
        {
          "timestamp": "2025-08-03T00:30:00+00:00",
          "glucose": 57.0
        },
        {
          "timestamp": "2025-08-03T00:40:00+00:00",
          "glucose": 56.0
        },
        {
          "timestamp": "2025-08-03T01:00:00+00:00",
          "glucose": 69.0
        },
        {
          "timestamp": "2025-08-03T01:05:00+00:00",
          "glucose": 55.0
        },
        {
          "timestamp": "2025-08-03T01:10:00+00:00",
          "glucose": 57.0
        },
        {
          "timestamp": "2025-08-03T01:15:00+00:00",
          "glucose": 46.0
        },
        {
          "timestamp": "2025-08-03T01:20:00+00:00",
          "glucose": 41.0
        },
        {
          "timestamp": "2025-08-03T01:25:00+00:00",
          "glucose": 49.0
        },
        {
          "timestamp": "2025-08-03T01:30:00+00:00",
          "glucose": 66.0
        },
        {
          "timestamp": "2025-08-03T01:35:00+00:00",
          "glucose": 52.0
        },
        {
          "timestamp": "2025-08-03T01:40:00+00:00",
          "glucose": 38.0
        },
        {
          "timestamp": "2025-08-03T01:45:00+00:00",
          "glucose": 32.0
        },
        {
          "timestamp": "2025-08-03T01:50:00+00:00",
          "glucose": 30.0
        },
        {
          "timestamp": "2025-08-03T01:55:00+00:00",
          "glucose": 42.0
        },
        {
          "timestamp": "2025-08-03T02:00:00+00:00",
          "glucose": 35.0
        },
        {
          "timestamp": "2025-08-03T02:05:00+00:00",
          "glucose": 30.0
        },
        {
          "timestamp": "2025-08-03T02:10:00+00:00",
          "glucose": 39.0
        },
        {
          "timestamp": "2025-08-03T02:15:00+00:00",
          "glucose": 50.0
        },
        {
          "timestamp": "2025-08-03T02:20:00+00:00",
          "glucose": 49.0
        },
        {
          "timestamp": "2025-08-03T02:25:00+00:00",
          "glucose": 33.0
        },
        {
          "timestamp": "2025-08-03T02:30:00+00:00",
          "glucose": 30.0
        },
        {
          "timestamp": "2025-08-03T02:35:00+00:00",
          "glucose": 37.0
        },
        {
          "timestamp": "2025-08-03T02:40:00+00:00",
          "glucose": 55.0
        },
        {
          "timestamp": "2025-08-03T02:45:00+00:00",
          "glucose": 66.0
        },
        {
          "timestamp": "2025-08-03T02:50:00+00:00",
          "glucose": 50.0
        },
        {
          "timestamp": "2025-08-03T02:55:00+00:00",
          "glucose": 37.0
        },
        {
          "timestamp": "2025-08-03T03:00:00+00:00",
          "glucose": 35.0
        },
        {
          "timestamp": "2025-08-03T03:05:00+00:00",
          "glucose": 31.0
        },
        {
          "timestamp": "2025-08-03T03:10:00+00:00",
          "glucose": 42.0
        },
        {
          "timestamp": "2025-08-03T03:15:00+00:00",
          "glucose": 42.0
        },
        {
          "timestamp": "2025-08-03T03:20:00+00:00",
          "glucose": 33.0
        },
        {
          "timestamp": "2025-08-03T03:25:00+00:00",
          "glucose": 30.0
        },
        {
          "timestamp": "2025-08-03T03:30:00+00:00",
          "glucose": 30.0
        },
        {
          "timestamp": "2025-08-03T03:35:00+00:00",
          "glucose": 30.0
        },
        {
          "timestamp": "2025-08-03T03:40:00+00:00",
          "glucose": 42.0
        },
        {
          "timestamp": "2025-08-03T03:45:00+00:00",
          "glucose": 52.0
        },
        {
          "timestamp": "2025-08-03T03:50:00+00:00",
          "glucose": 39.0
        },
        {
          "timestamp": "2025-08-03T03:55:00+00:00",
          "glucose": 30.0
        },
        {
          "timestamp": "2025-08-03T04:00:00+00:00",
          "glucose": 55.0
        },
        {
          "timestamp": "2025-08-03T04:05:00+00:00",
          "glucose": 47.0
        },
        {
          "timestamp": "2025-08-03T04:10:00+00:00",
          "glucose": 37.0
        },
        {
          "timestamp": "2025-08-03T04:15:00+00:00",
          "glucose": 51.0
        },
        {
          "timestamp": "2025-08-03T04:20:00+00:00",
          "glucose": 35.0
        },
        {
          "timestamp": "2025-08-03T04:25:00+00:00",
          "glucose": 30.0
        },
        {
          "timestamp": "2025-08-03T04:30:00+00:00",
          "glucose": 43.0
        },
        {
          "timestamp": "2025-08-03T04:35:00+00:00",
          "glucose": 38.0
        },
        {
          "timestamp": "2025-08-03T04:40:00+00:00",
          "glucose": 30.0
        },
        {
          "timestamp": "2025-08-03T04:45:00+00:00",
          "glucose": 30.0
        },
        {
          "timestamp": "2025-08-03T04:50:00+00:00",
          "glucose": 35.0
        },
        {
          "timestamp": "2025-08-03T04:55:00+00:00",
          "glucose": 33.0
        },
        {
          "timestamp": "2025-08-03T05:00:00+00:00",
          "glucose": 43.0
        },
        {
          "timestamp": "2025-08-03T05:05:00+00:00",
          "glucose": 30.0
        },
        {
          "timestamp": "2025-08-03T05:10:00+00:00",
          "glucose": 36.0
        },
        {
          "timestamp": "2025-08-03T05:15:00+00:00",
          "glucose": 47.0
        },
        {
          "timestamp": "2025-08-03T05:20:00+00:00",
          "glucose": 31.0
        },
        {
          "timestamp": "2025-08-03T05:25:00+00:00",
          "glucose": 40.0
        },
        {
          "timestamp": "2025-08-03T05:30:00+00:00",
          "glucose": 30.0
        },
        {
          "timestamp": "2025-08-03T05:35:00+00:00",
          "glucose": 32.0
        },
        {
          "timestamp": "2025-08-03T05:40:00+00:00",
          "glucose": 38.0
        },
        {
          "timestamp": "2025-08-03T05:45:00+00:00",
          "glucose": 38.0
        },
        {
          "timestamp": "2025-08-03T05:50:00+00:00",
          "glucose": 30.0
        },
        {
          "timestamp": "2025-08-03T05:55:00+00:00",
          "glucose": 44.0
        },
        {
          "timestamp": "2025-08-03T06:00:00+00:00",
          "glucose": 46.0
        },
        {
          "timestamp": "2025-08-03T06:05:00+00:00",
          "glucose": 60.0
        },
        {
          "timestamp": "2025-08-03T06:10:00+00:00",
          "glucose": 59.0
        },
        {
          "timestamp": "2025-08-03T06:15:00+00:00",
          "glucose": 64.0
        },
        {
          "timestamp": "2025-08-03T06:25:00+00:00",
          "glucose": 61.0
        },
        {
          "timestamp": "2025-08-03T06:30:00+00:00",
          "glucose": 45.0
        },
        {
          "timestamp": "2025-08-03T06:35:00+00:00",
          "glucose": 60.0
        },
        {
          "timestamp": "2025-08-03T06:45:00+00:00",
          "glucose": 62.0
        },
        {
          "timestamp": "2025-08-03T06:55:00+00:00",
          "glucose": 59.0
        },
        {
          "timestamp": "2025-08-03T07:00:00+00:00",
          "glucose": 45.0
        },
        {
          "timestamp": "2025-08-03T07:05:00+00:00",
          "glucose": 40.0
        },
        {
          "timestamp": "2025-08-03T07:10:00+00:00",
          "glucose": 58.0
        }
      ],
      "nocturnal_hypoglycemia_events": [
        {
          "timestamp": "2025-08-01T23:45:00+00:00",
          "glucose": 66.0
        },
        {
          "timestamp": "2025-08-03T00:00:00+00:00",
          "glucose": 40.0
        },
        {
          "timestamp": "2025-08-03T00:05:00+00:00",
          "glucose": 60.0
        },
        {
          "timestamp": "2025-08-03T00:25:00+00:00",
          "glucose": 61.0
        },
        {
          "timestamp": "2025-08-03T00:30:00+00:00",
          "glucose": 57.0
        },
        {
          "timestamp": "2025-08-03T00:40:00+00:00",
          "glucose": 56.0
        },
        {
          "timestamp": "2025-08-03T01:00:00+00:00",
          "glucose": 69.0
        },
        {
          "timestamp": "2025-08-03T01:05:00+00:00",
          "glucose": 55.0
        },
        {
          "timestamp": "2025-08-03T01:10:00+00:00",
          "glucose": 57.0
        },
        {
          "timestamp": "2025-08-03T01:15:00+00:00",
          "glucose": 46.0
        },
        {
          "timestamp": "2025-08-03T01:20:00+00:00",
          "glucose": 41.0
        },
        {
          "timestamp": "2025-08-03T01:25:00+00:00",
          "glucose": 49.0
        },
        {
          "timestamp": "2025-08-03T01:30:00+00:00",
          "glucose": 66.0
        },
        {
          "timestamp": "2025-08-03T01:35:00+00:00",
          "glucose": 52.0
        },
        {
          "timestamp": "2025-08-03T01:40:00+00:00",
          "glucose": 38.0
        },
        {
          "timestamp": "2025-08-03T01:45:00+00:00",
          "glucose": 32.0
        },
        {
          "timestamp": "2025-08-03T01:50:00+00:00",
          "glucose": 30.0
        },
        {
          "timestamp": "2025-08-03T01:55:00+00:00",
          "glucose": 42.0
        },
        {
          "timestamp": "2025-08-03T02:00:00+00:00",
          "glucose": 35.0
        },
        {
          "timestamp": "2025-08-03T02:05:00+00:00",
          "glucose": 30.0
        },
        {
          "timestamp": "2025-08-03T02:10:00+00:00",
          "glucose": 39.0
        },
        {
          "timestamp": "2025-08-03T02:15:00+00:00",
          "glucose": 50.0
        },
        {
          "timestamp": "2025-08-03T02:20:00+00:00",
          "glucose": 49.0
        },
        {
          "timestamp": "2025-08-03T02:25:00+00:00",
          "glucose": 33.0
        },
        {
          "timestamp": "2025-08-03T02:30:00+00:00",
          "glucose": 30.0
        },
        {
          "timestamp": "2025-08-03T02:35:00+00:00",
          "glucose": 37.0
        },
        {
          "timestamp": "2025-08-03T02:40:00+00:00",
          "glucose": 55.0
        },
        {
          "timestamp": "2025-08-03T02:45:00+00:00",
          "glucose": 66.0
        },
        {
          "timestamp": "2025-08-03T02:50:00+00:00",
          "glucose": 50.0
        },
        {
          "timestamp": "2025-08-03T02:55:00+00:00",
          "glucose": 37.0
        },
        {
          "timestamp": "2025-08-03T03:00:00+00:00",
          "glucose": 35.0
        },
        {
          "timestamp": "2025-08-03T03:05:00+00:00",
          "glucose": 31.0
        },
        {
          "timestamp": "2025-08-03T03:10:00+00:00",
          "glucose": 42.0
        },
        {
          "timestamp": "2025-08-03T03:15:00+00:00",
          "glucose": 42.0
        },
        {
          "timestamp": "2025-08-03T03:20:00+00:00",
          "glucose": 33.0
        },
        {
          "timestamp": "2025-08-03T03:25:00+00:00",
          "glucose": 30.0
        },
        {
          "timestamp": "2025-08-03T03:30:00+00:00",
          "glucose": 30.0
        },
        {
          "timestamp": "2025-08-03T03:35:00+00:00",
          "glucose": 30.0
        },
        {
          "timestamp": "2025-08-03T03:40:00+00:00",
          "glucose": 42.0
        },
        {
          "timestamp": "2025-08-03T03:45:00+00:00",
          "glucose": 52.0
        },
        {
          "timestamp": "2025-08-03T03:50:00+00:00",
          "glucose": 39.0
        },
        {
          "timestamp": "2025-08-03T03:55:00+00:00",
          "glucose": 30.0
        },
        {
          "timestamp": "2025-08-03T04:00:00+00:00",
          "glucose": 55.0
        },
        {
          "timestamp": "2025-08-03T04:05:00+00:00",
          "glucose": 47.0
        },
        {
          "timestamp": "2025-08-03T04:10:00+00:00",
          "glucose": 37.0
        },
        {
          "timestamp": "2025-08-03T04:15:00+00:00",
          "glucose": 51.0
        },
        {
          "timestamp": "2025-08-03T04:20:00+00:00",
          "glucose": 35.0
        },
        {
          "timestamp": "2025-08-03T04:25:00+00:00",
          "glucose": 30.0
        },
        {
          "timestamp": "2025-08-03T04:30:00+00:00",
          "glucose": 43.0
        },
        {
          "timestamp": "2025-08-03T04:35:00+00:00",
          "glucose": 38.0
        },
        {
          "timestamp": "2025-08-03T04:40:00+00:00",
          "glucose": 30.0
        },
        {
          "timestamp": "2025-08-03T04:45:00+00:00",
          "glucose": 30.0
        },
        {
          "timestamp": "2025-08-03T04:50:00+00:00",
          "glucose": 35.0
        },
        {
          "timestamp": "2025-08-03T04:55:00+00:00",
          "glucose": 33.0
        },
        {
          "timestamp": "2025-08-03T05:00:00+00:00",
          "glucose": 43.0
        },
        {
          "timestamp": "2025-08-03T05:05:00+00:00",
          "glucose": 30.0
        },
        {
          "timestamp": "2025-08-03T05:10:00+00:00",
          "glucose": 36.0
        },
        {
          "timestamp": "2025-08-03T05:15:00+00:00",
          "glucose": 47.0
        },
        {
          "timestamp": "2025-08-03T05:20:00+00:00",
          "glucose": 31.0
        },
        {
          "timestamp": "2025-08-03T05:25:00+00:00",
          "glucose": 40.0
        },
        {
          "timestamp": "2025-08-03T05:30:00+00:00",
          "glucose": 30.0
        },
        {
          "timestamp": "2025-08-03T05:35:00+00:00",
          "glucose": 32.0
        },
        {
          "timestamp": "2025-08-03T05:40:00+00:00",
          "glucose": 38.0
        },
        {
          "timestamp": "2025-08-03T05:45:00+00:00",
          "glucose": 38.0
        },
        {
          "timestamp": "2025-08-03T05:50:00+00:00",
          "glucose": 30.0
        },
        {
          "timestamp": "2025-08-03T05:55:00+00:00",
          "glucose": 44.0
        }
      ],
      "nocturnal_hypoglycemia_episodes": [
        {
          "start": "2025-08-01T23:45:00+00:00",
          "end": "2025-08-01T23:45:00+00:00",
          "min_glucose": 66.0,
          "count": 1
        },
        {
          "start": "2025-08-03T00:00:00+00:00",
          "end": "2025-08-03T05:55:00+00:00",
          "min_glucose": 30.0,
          "count": 65
        }
      ],
      "hyperglycemia_events": [
        {
          "timestamp": "2025-08-01T00:00:00+00:00",
          "glucose": 307.0
        },
        {
          "timestamp": "2025-08-01T00:05:00+00:00",
          "glucose": 309.0
        },
        {
          "timestamp": "2025-08-01T00:10:00+00:00",
          "glucose": 326.0
        },
        {
          "timestamp": "2025-08-01T00:15:00+00:00",
          "glucose": 316.0
        },
        {
          "timestamp": "2025-08-01T00:20:00+00:00",
          "glucose": 311.0
        },
        {
          "timestamp": "2025-08-01T00:25:00+00:00",
          "glucose": 331.0
        },
        {
          "timestamp": "2025-08-01T00:30:00+00:00",
          "glucose": 311.0
        },
        {
          "timestamp": "2025-08-01T00:35:00+00:00",
          "glucose": 318.0
        },
        {
          "timestamp": "2025-08-01T00:40:00+00:00",
          "glucose": 304.0
        },
        {
          "timestamp": "2025-08-01T00:45:00+00:00",
          "glucose": 300.0
        },
        {
          "timestamp": "2025-08-01T00:50:00+00:00",
          "glucose": 317.0
        },
        {
          "timestamp": "2025-08-01T00:55:00+00:00",
          "glucose": 308.0
        },
        {
          "timestamp": "2025-08-01T01:00:00+00:00",
          "glucose": 293.0
        },
        {
          "timestamp": "2025-08-01T01:05:00+00:00",
          "glucose": 297.0
        },
        {
          "timestamp": "2025-08-01T01:10:00+00:00",
          "glucose": 292.0
        },
        {
          "timestamp": "2025-08-01T01:15:00+00:00",
          "glucose": 278.0
        },
        {
          "timestamp": "2025-08-01T01:20:00+00:00",
          "glucose": 283.0
        },
        {
          "timestamp": "2025-08-01T01:25:00+00:00",
          "glucose": 292.0
        },
        {
          "timestamp": "2025-08-01T01:30:00+00:00",
          "glucose": 302.0
        },
        {
          "timestamp": "2025-08-01T01:35:00+00:00",
          "glucose": 287.0
        },
        {
          "timestamp": "2025-08-01T01:40:00+00:00",
          "glucose": 285.0
        },
        {
          "timestamp": "2025-08-01T01:45:00+00:00",
          "glucose": 277.0
        },
        {
          "timestamp": "2025-08-01T01:50:00+00:00",
          "glucose": 288.0
        },
        {
          "timestamp": "2025-08-01T01:55:00+00:00",
          "glucose": 299.0
        },
        {
          "timestamp": "2025-08-01T02:00:00+00:00",
          "glucose": 290.0
        },
        {
          "timestamp": "2025-08-01T02:05:00+00:00",
          "glucose": 306.0
        },
        {
          "timestamp": "2025-08-01T02:10:00+00:00",
          "glucose": 306.0
        },
        {
          "timestamp": "2025-08-01T02:15:00+00:00",
          "glucose": 290.0
        },
        {
          "timestamp": "2025-08-01T02:20:00+00:00",
          "glucose": 278.0
        },
        {
          "timestamp": "2025-08-01T02:25:00+00:00",
          "glucose": 298.0
        },
        {
          "timestamp": "2025-08-01T02:30:00+00:00",
          "glucose": 318.0
        },
        {
          "timestamp": "2025-08-01T02:35:00+00:00",
          "glucose": 332.0
        },
        {
          "timestamp": "2025-08-01T02:40:00+00:00",
          "glucose": 337.0
        },
        {
          "timestamp": "2025-08-01T02:45:00+00:00",
          "glucose": 355.0
        },
        {
          "timestamp": "2025-08-01T02:50:00+00:00",
          "glucose": 348.0
        },
        {
          "timestamp": "2025-08-01T02:55:00+00:00",
          "glucose": 340.0
        },
        {
          "timestamp": "2025-08-01T03:00:00+00:00",
          "glucose": 345.0
        },
        {
          "timestamp": "2025-08-01T03:05:00+00:00",
          "glucose": 331.0
        },
        {
          "timestamp": "2025-08-01T03:10:00+00:00",
          "glucose": 340.0
        },
        {
          "timestamp": "2025-08-01T03:15:00+00:00",
          "glucose": 323.0
        },
        {
          "timestamp": "2025-08-01T03:20:00+00:00",
          "glucose": 320.0
        },
        {
          "timestamp": "2025-08-01T03:25:00+00:00",
          "glucose": 334.0
        },
        {
          "timestamp": "2025-08-01T03:30:00+00:00",
          "glucose": 326.0
        },
        {
          "timestamp": "2025-08-01T03:35:00+00:00",
          "glucose": 334.0
        },
        {
          "timestamp": "2025-08-01T03:40:00+00:00",
          "glucose": 318.0
        },
        {
          "timestamp": "2025-08-01T03:45:00+00:00",
          "glucose": 308.0
        },
        {
          "timestamp": "2025-08-01T03:50:00+00:00",
          "glucose": 320.0
        },
        {
          "timestamp": "2025-08-01T03:55:00+00:00",
          "glucose": 314.0
        },
        {
          "timestamp": "2025-08-01T04:00:00+00:00",
          "glucose": 318.0
        },
        {
          "timestamp": "2025-08-01T04:05:00+00:00",
          "glucose": 299.0
        },
        {
          "timestamp": "2025-08-01T04:10:00+00:00",
          "glucose": 302.0
        },
        {
          "timestamp": "2025-08-01T04:15:00+00:00",
          "glucose": 309.0
        },
        {
          "timestamp": "2025-08-01T04:20:00+00:00",
          "glucose": 303.0
        },
        {
          "timestamp": "2025-08-01T04:25:00+00:00",
          "glucose": 296.0
        },
        {
          "timestamp": "2025-08-01T04:30:00+00:00",
          "glucose": 277.0
        },
        {
          "timestamp": "2025-08-01T04:35:00+00:00",
          "glucose": 286.0
        },
        {
          "timestamp": "2025-08-01T04:40:00+00:00",
          "glucose": 281.0
        },
        {
          "timestamp": "2025-08-01T04:45:00+00:00",
          "glucose": 266.0
        },
        {
          "timestamp": "2025-08-01T04:50:00+00:00",
          "glucose": 255.0
        },
        {
          "timestamp": "2025-08-01T04:55:00+00:00",
          "glucose": 240.0
        },
        {
          "timestamp": "2025-08-01T05:00:00+00:00",
          "glucose": 254.0
        },
        {
          "timestamp": "2025-08-01T05:05:00+00:00",
          "glucose": 237.0
        },
        {
          "timestamp": "2025-08-01T05:10:00+00:00",
          "glucose": 239.0
        },
        {
          "timestamp": "2025-08-01T05:15:00+00:00",
          "glucose": 229.0
        },
        {
          "timestamp": "2025-08-01T05:20:00+00:00",
          "glucose": 214.0
        },
        {
          "timestamp": "2025-08-01T05:25:00+00:00",
          "glucose": 231.0
        },
        {
          "timestamp": "2025-08-01T05:30:00+00:00",
          "glucose": 214.0
        },
        {
          "timestamp": "2025-08-01T05:35:00+00:00",
          "glucose": 219.0
        },
        {
          "timestamp": "2025-08-01T05:40:00+00:00",
          "glucose": 237.0
        },
        {
          "timestamp": "2025-08-01T05:45:00+00:00",
          "glucose": 250.0
        },
        {
          "timestamp": "2025-08-01T05:50:00+00:00",
          "glucose": 230.0
        },
        {
          "timestamp": "2025-08-01T05:55:00+00:00",
          "glucose": 231.0
        },
        {
          "timestamp": "2025-08-01T06:00:00+00:00",
          "glucose": 244.0
        },
        {
          "timestamp": "2025-08-01T06:05:00+00:00",
          "glucose": 233.0
        },
        {
          "timestamp": "2025-08-01T06:10:00+00:00",
          "glucose": 230.0
        },
        {
          "timestamp": "2025-08-01T06:15:00+00:00",
          "glucose": 219.0
        },
        {
          "timestamp": "2025-08-01T06:20:00+00:00",
          "glucose": 211.0
        },
        {
          "timestamp": "2025-08-01T06:25:00+00:00",
          "glucose": 218.0
        },
        {
          "timestamp": "2025-08-01T06:30:00+00:00",
          "glucose": 230.0
        },
        {
          "timestamp": "2025-08-01T06:35:00+00:00",
          "glucose": 246.0
        },
        {
          "timestamp": "2025-08-01T06:40:00+00:00",
          "glucose": 252.0
        },
        {
          "timestamp": "2025-08-01T06:45:00+00:00",
          "glucose": 263.0
        },
        {
          "timestamp": "2025-08-01T06:50:00+00:00",
          "glucose": 268.0
        },
        {
          "timestamp": "2025-08-01T06:55:00+00:00",
          "glucose": 252.0
        },
        {
          "timestamp": "2025-08-01T07:00:00+00:00",
          "glucose": 269.0
        },
        {
          "timestamp": "2025-08-01T07:05:00+00:00",
          "glucose": 255.0
        },
        {
          "timestamp": "2025-08-01T07:10:00+00:00",
          "glucose": 240.0
        },
        {
          "timestamp": "2025-08-01T07:15:00+00:00",
          "glucose": 246.0
        },
        {
          "timestamp": "2025-08-01T07:20:00+00:00",
          "glucose": 258.0
        },
        {
          "timestamp": "2025-08-01T07:25:00+00:00",
          "glucose": 277.0
        },
        {
          "timestamp": "2025-08-01T07:30:00+00:00",
          "glucose": 287.0
        },
        {
          "timestamp": "2025-08-01T07:35:00+00:00",
          "glucose": 297.0
        },
        {
          "timestamp": "2025-08-01T07:40:00+00:00",
          "glucose": 311.0
        },
        {
          "timestamp": "2025-08-01T07:45:00+00:00",
          "glucose": 327.0
        },
        {
          "timestamp": "2025-08-01T07:50:00+00:00",
          "glucose": 332.0
        },
        {
          "timestamp": "2025-08-01T07:55:00+00:00",
          "glucose": 322.0
        },
        {
          "timestamp": "2025-08-01T16:00:00+00:00",
          "glucose": 360.0
        },
        {
          "timestamp": "2025-08-01T16:05:00+00:00",
          "glucose": 342.0
        },
        {
          "timestamp": "2025-08-01T16:10:00+00:00",
          "glucose": 344.0
        },
        {
          "timestamp": "2025-08-01T16:15:00+00:00",
          "glucose": 341.0
        },
        {
          "timestamp": "2025-08-01T16:20:00+00:00",
          "glucose": 322.0
        },
        {
          "timestamp": "2025-08-01T16:25:00+00:00",
          "glucose": 341.0
        },
        {
          "timestamp": "2025-08-01T16:30:00+00:00",
          "glucose": 336.0
        },
        {
          "timestamp": "2025-08-01T16:35:00+00:00",
          "glucose": 338.0
        },
        {
          "timestamp": "2025-08-01T16:40:00+00:00",
          "glucose": 320.0
        },
        {
          "timestamp": "2025-08-01T16:45:00+00:00",
          "glucose": 304.0
        },
        {
          "timestamp": "2025-08-01T16:50:00+00:00",
          "glucose": 308.0
        },
        {
          "timestamp": "2025-08-01T16:55:00+00:00",
          "glucose": 301.0
        },
        {
          "timestamp": "2025-08-01T17:00:00+00:00",
          "glucose": 312.0
        },
        {
          "timestamp": "2025-08-01T17:05:00+00:00",
          "glucose": 307.0
        },
        {
          "timestamp": "2025-08-01T17:10:00+00:00",
          "glucose": 312.0
        },
        {
          "timestamp": "2025-08-01T17:15:00+00:00",
          "glucose": 292.0
        },
        {
          "timestamp": "2025-08-01T17:20:00+00:00",
          "glucose": 306.0
        },
        {
          "timestamp": "2025-08-01T17:25:00+00:00",
          "glucose": 286.0
        },
        {
          "timestamp": "2025-08-01T17:30:00+00:00",
          "glucose": 291.0
        },
        {
          "timestamp": "2025-08-01T17:35:00+00:00",
          "glucose": 277.0
        },
        {
          "timestamp": "2025-08-01T17:40:00+00:00",
          "glucose": 289.0
        },
        {
          "timestamp": "2025-08-01T17:45:00+00:00",
          "glucose": 296.0
        },
        {
          "timestamp": "2025-08-01T17:50:00+00:00",
          "glucose": 310.0
        },
        {
          "timestamp": "2025-08-01T17:55:00+00:00",
          "glucose": 315.0
        },
        {
          "timestamp": "2025-08-01T18:00:00+00:00",
          "glucose": 313.0
        },
        {
          "timestamp": "2025-08-01T18:05:00+00:00",
          "glucose": 318.0
        },
        {
          "timestamp": "2025-08-01T18:10:00+00:00",
          "glucose": 319.0
        },
        {
          "timestamp": "2025-08-01T18:15:00+00:00",
          "glucose": 312.0
        },
        {
          "timestamp": "2025-08-01T18:20:00+00:00",
          "glucose": 322.0
        },
        {
          "timestamp": "2025-08-01T18:25:00+00:00",
          "glucose": 306.0
        },
        {
          "timestamp": "2025-08-01T18:30:00+00:00",
          "glucose": 287.0
        },
        {
          "timestamp": "2025-08-01T18:35:00+00:00",
          "glucose": 276.0
        },
        {
          "timestamp": "2025-08-01T18:40:00+00:00",
          "glucose": 268.0
        },
        {
          "timestamp": "2025-08-01T18:45:00+00:00",
          "glucose": 251.0
        },
        {
          "timestamp": "2025-08-01T18:50:00+00:00",
          "glucose": 271.0
        },
        {
          "timestamp": "2025-08-01T18:55:00+00:00",
          "glucose": 287.0
        },
        {
          "timestamp": "2025-08-01T19:00:00+00:00",
          "glucose": 268.0
        },
        {
          "timestamp": "2025-08-01T19:05:00+00:00",
          "glucose": 281.0
        },
        {
          "timestamp": "2025-08-01T19:10:00+00:00",
          "glucose": 300.0
        },
        {
          "timestamp": "2025-08-01T19:15:00+00:00",
          "glucose": 282.0
        },
        {
          "timestamp": "2025-08-01T19:20:00+00:00",
          "glucose": 297.0
        },
        {
          "timestamp": "2025-08-01T19:25:00+00:00",
          "glucose": 297.0
        },
        {
          "timestamp": "2025-08-01T19:30:00+00:00",
          "glucose": 292.0
        },
        {
          "timestamp": "2025-08-01T19:35:00+00:00",
          "glucose": 283.0
        },
        {
          "timestamp": "2025-08-01T19:40:00+00:00",
          "glucose": 285.0
        },
        {
          "timestamp": "2025-08-01T19:45:00+00:00",
          "glucose": 272.0
        },
        {
          "timestamp": "2025-08-01T19:50:00+00:00",
          "glucose": 259.0
        },
        {
          "timestamp": "2025-08-01T19:55:00+00:00",
          "glucose": 250.0
        },
        {
          "timestamp": "2025-08-02T00:00:00+00:00",
          "glucose": 306.0
        },
        {
          "timestamp": "2025-08-02T00:05:00+00:00",
          "glucose": 292.0
        },
        {
          "timestamp": "2025-08-02T00:10:00+00:00",
          "glucose": 289.0
        },
        {
          "timestamp": "2025-08-02T00:15:00+00:00",
          "glucose": 304.0
        },
        {
          "timestamp": "2025-08-02T00:20:00+00:00",
          "glucose": 316.0
        },
        {
          "timestamp": "2025-08-02T00:25:00+00:00",
          "glucose": 307.0
        },
        {
          "timestamp": "2025-08-02T00:30:00+00:00",
          "glucose": 312.0
        },
        {
          "timestamp": "2025-08-02T00:35:00+00:00",
          "glucose": 294.0
        },
        {
          "timestamp": "2025-08-02T00:40:00+00:00",
          "glucose": 309.0
        },
        {
          "timestamp": "2025-08-02T00:45:00+00:00",
          "glucose": 301.0
        },
        {
          "timestamp": "2025-08-02T00:50:00+00:00",
          "glucose": 320.0
        },
        {
          "timestamp": "2025-08-02T00:55:00+00:00",
          "glucose": 330.0
        },
        {
          "timestamp": "2025-08-02T01:00:00+00:00",
          "glucose": 312.0
        },
        {
          "timestamp": "2025-08-02T01:05:00+00:00",
          "glucose": 330.0
        },
        {
          "timestamp": "2025-08-02T01:10:00+00:00",
          "glucose": 347.0
        },
        {
          "timestamp": "2025-08-02T01:15:00+00:00",
          "glucose": 353.0
        },
        {
          "timestamp": "2025-08-02T01:20:00+00:00",
          "glucose": 365.0
        },
        {
          "timestamp": "2025-08-02T01:25:00+00:00",
          "glucose": 372.0
        },
        {
          "timestamp": "2025-08-02T01:30:00+00:00",
          "glucose": 373.0
        },
        {
          "timestamp": "2025-08-02T01:35:00+00:00",
          "glucose": 391.0
        },
        {
          "timestamp": "2025-08-02T01:40:00+00:00",
          "glucose": 409.0
        },
        {
          "timestamp": "2025-08-02T01:45:00+00:00",
          "glucose": 414.0
        },
        {
          "timestamp": "2025-08-02T01:50:00+00:00",
          "glucose": 406.0
        },
        {
          "timestamp": "2025-08-02T01:55:00+00:00",
          "glucose": 393.0
        },
        {
          "timestamp": "2025-08-02T02:00:00+00:00",
          "glucose": 380.0
        },
        {
          "timestamp": "2025-08-02T02:05:00+00:00",
          "glucose": 385.0
        },
        {
          "timestamp": "2025-08-02T02:10:00+00:00",
          "glucose": 397.0
        },
        {
          "timestamp": "2025-08-02T02:15:00+00:00",
          "glucose": 377.0
        },
        {
          "timestamp": "2025-08-02T02:20:00+00:00",
          "glucose": 365.0
        },
        {
          "timestamp": "2025-08-02T02:25:00+00:00",
          "glucose": 370.0
        },
        {
          "timestamp": "2025-08-02T02:30:00+00:00",
          "glucose": 374.0
        },
        {
          "timestamp": "2025-08-02T02:35:00+00:00",
          "glucose": 391.0
        },
        {
          "timestamp": "2025-08-02T02:40:00+00:00",
          "glucose": 374.0
        },
        {
          "timestamp": "2025-08-02T02:45:00+00:00",
          "glucose": 380.0
        },
        {
          "timestamp": "2025-08-02T02:50:00+00:00",
          "glucose": 376.0
        },
        {
          "timestamp": "2025-08-02T02:55:00+00:00",
          "glucose": 387.0
        },
        {
          "timestamp": "2025-08-02T03:00:00+00:00",
          "glucose": 394.0
        },
        {
          "timestamp": "2025-08-02T03:05:00+00:00",
          "glucose": 408.0
        },
        {
          "timestamp": "2025-08-02T03:10:00+00:00",
          "glucose": 397.0
        },
        {
          "timestamp": "2025-08-02T03:15:00+00:00",
          "glucose": 386.0
        },
        {
          "timestamp": "2025-08-02T03:20:00+00:00",
          "glucose": 384.0
        },
        {
          "timestamp": "2025-08-02T03:25:00+00:00",
          "glucose": 404.0
        },
        {
          "timestamp": "2025-08-02T03:30:00+00:00",
          "glucose": 384.0
        },
        {
          "timestamp": "2025-08-02T03:35:00+00:00",
          "glucose": 368.0
        },
        {
          "timestamp": "2025-08-02T03:40:00+00:00",
          "glucose": 388.0
        },
        {
          "timestamp": "2025-08-02T03:45:00+00:00",
          "glucose": 404.0
        },
        {
          "timestamp": "2025-08-02T03:50:00+00:00",
          "glucose": 401.0
        },
        {
          "timestamp": "2025-08-02T03:55:00+00:00",
          "glucose": 383.0
        },
        {
          "timestamp": "2025-08-02T04:00:00+00:00",
          "glucose": 347.0
        },
        {
          "timestamp": "2025-08-02T04:05:00+00:00",
          "glucose": 331.0
        },
        {
          "timestamp": "2025-08-02T04:10:00+00:00",
          "glucose": 339.0
        },
        {
          "timestamp": "2025-08-02T04:15:00+00:00",
          "glucose": 336.0
        },
        {
          "timestamp": "2025-08-02T04:20:00+00:00",
          "glucose": 348.0
        },
        {
          "timestamp": "2025-08-02T04:25:00+00:00",
          "glucose": 342.0
        },
        {
          "timestamp": "2025-08-02T04:30:00+00:00",
          "glucose": 342.0
        },
        {
          "timestamp": "2025-08-02T04:35:00+00:00",
          "glucose": 350.0
        },
        {
          "timestamp": "2025-08-02T04:40:00+00:00",
          "glucose": 364.0
        },
        {
          "timestamp": "2025-08-02T04:45:00+00:00",
          "glucose": 368.0
        },
        {
          "timestamp": "2025-08-02T04:50:00+00:00",
          "glucose": 349.0
        },
        {
          "timestamp": "2025-08-02T04:55:00+00:00",
          "glucose": 368.0
        },
        {
          "timestamp": "2025-08-02T05:00:00+00:00",
          "glucose": 363.0
        },
        {
          "timestamp": "2025-08-02T05:05:00+00:00",
          "glucose": 357.0
        },
        {
          "timestamp": "2025-08-02T05:10:00+00:00",
          "glucose": 337.0
        },
        {
          "timestamp": "2025-08-02T05:15:00+00:00",
          "glucose": 318.0
        },
        {
          "timestamp": "2025-08-02T05:20:00+00:00",
          "glucose": 330.0
        },
        {
          "timestamp": "2025-08-02T05:25:00+00:00",
          "glucose": 333.0
        },
        {
          "timestamp": "2025-08-02T05:30:00+00:00",
          "glucose": 321.0
        },
        {
          "timestamp": "2025-08-02T05:35:00+00:00",
          "glucose": 315.0
        },
        {
          "timestamp": "2025-08-02T05:40:00+00:00",
          "glucose": 317.0
        },
        {
          "timestamp": "2025-08-02T05:45:00+00:00",
          "glucose": 302.0
        },
        {
          "timestamp": "2025-08-02T05:50:00+00:00",
          "glucose": 288.0
        },
        {
          "timestamp": "2025-08-02T05:55:00+00:00",
          "glucose": 277.0
        },
        {
          "timestamp": "2025-08-02T06:00:00+00:00",
          "glucose": 279.0
        },
        {
          "timestamp": "2025-08-02T06:05:00+00:00",
          "glucose": 285.0
        },
        {
          "timestamp": "2025-08-02T06:10:00+00:00",
          "glucose": 305.0
        },
        {
          "timestamp": "2025-08-02T06:15:00+00:00",
          "glucose": 302.0
        },
        {
          "timestamp": "2025-08-02T06:20:00+00:00",
          "glucose": 317.0
        },
        {
          "timestamp": "2025-08-02T06:25:00+00:00",
          "glucose": 299.0
        },
        {
          "timestamp": "2025-08-02T06:30:00+00:00",
          "glucose": 299.0
        },
        {
          "timestamp": "2025-08-02T06:35:00+00:00",
          "glucose": 289.0
        },
        {
          "timestamp": "2025-08-02T06:40:00+00:00",
          "glucose": 277.0
        },
        {
          "timestamp": "2025-08-02T06:45:00+00:00",
          "glucose": 259.0
        },
        {
          "timestamp": "2025-08-02T06:50:00+00:00",
          "glucose": 271.0
        },
        {
          "timestamp": "2025-08-02T06:55:00+00:00",
          "glucose": 260.0
        },
        {
          "timestamp": "2025-08-02T07:00:00+00:00",
          "glucose": 261.0
        },
        {
          "timestamp": "2025-08-02T07:05:00+00:00",
          "glucose": 260.0
        },
        {
          "timestamp": "2025-08-02T07:10:00+00:00",
          "glucose": 262.0
        },
        {
          "timestamp": "2025-08-02T07:15:00+00:00",
          "glucose": 259.0
        },
        {
          "timestamp": "2025-08-02T07:20:00+00:00",
          "glucose": 247.0
        },
        {
          "timestamp": "2025-08-02T07:25:00+00:00",
          "glucose": 256.0
        },
        {
          "timestamp": "2025-08-02T07:30:00+00:00",
          "glucose": 264.0
        },
        {
          "timestamp": "2025-08-02T07:35:00+00:00",
          "glucose": 265.0
        },
        {
          "timestamp": "2025-08-02T07:40:00+00:00",
          "glucose": 254.0
        },
        {
          "timestamp": "2025-08-02T07:45:00+00:00",
          "glucose": 268.0
        },
        {
          "timestamp": "2025-08-02T07:50:00+00:00",
          "glucose": 265.0
        },
        {
          "timestamp": "2025-08-02T07:55:00+00:00",
          "glucose": 278.0
        },
        {
          "timestamp": "2025-08-02T15:10:00+00:00",
          "glucose": 192.0
        },
        {
          "timestamp": "2025-08-02T15:15:00+00:00",
          "glucose": 200.0
        },
        {
          "timestamp": "2025-08-02T15:20:00+00:00",
          "glucose": 214.0
        },
        {
          "timestamp": "2025-08-02T15:25:00+00:00",
          "glucose": 231.0
        },
        {
          "timestamp": "2025-08-02T15:30:00+00:00",
          "glucose": 246.0
        },
        {
          "timestamp": "2025-08-02T15:35:00+00:00",
          "glucose": 238.0
        },
        {
          "timestamp": "2025-08-02T15:40:00+00:00",
          "glucose": 233.0
        },
        {
          "timestamp": "2025-08-02T15:45:00+00:00",
          "glucose": 247.0
        },
        {
          "timestamp": "2025-08-02T15:50:00+00:00",
          "glucose": 267.0
        },
        {
          "timestamp": "2025-08-02T15:55:00+00:00",
          "glucose": 276.0
        },
        {
          "timestamp": "2025-08-02T16:00:00+00:00",
          "glucose": 334.0
        },
        {
          "timestamp": "2025-08-02T16:05:00+00:00",
          "glucose": 335.0
        },
        {
          "timestamp": "2025-08-02T16:10:00+00:00",
          "glucose": 327.0
        },
        {
          "timestamp": "2025-08-02T16:15:00+00:00",
          "glucose": 314.0
        },
        {
          "timestamp": "2025-08-02T16:20:00+00:00",
          "glucose": 312.0
        },
        {
          "timestamp": "2025-08-02T16:25:00+00:00",
          "glucose": 329.0
        },
        {
          "timestamp": "2025-08-02T16:30:00+00:00",
          "glucose": 327.0
        },
        {
          "timestamp": "2025-08-02T16:35:00+00:00",
          "glucose": 337.0
        },
        {
          "timestamp": "2025-08-02T16:40:00+00:00",
          "glucose": 320.0
        },
        {
          "timestamp": "2025-08-02T16:45:00+00:00",
          "glucose": 313.0
        },
        {
          "timestamp": "2025-08-02T16:50:00+00:00",
          "glucose": 323.0
        },
        {
          "timestamp": "2025-08-02T16:55:00+00:00",
          "glucose": 305.0
        },
        {
          "timestamp": "2025-08-02T17:00:00+00:00",
          "glucose": 299.0
        },
        {
          "timestamp": "2025-08-02T17:05:00+00:00",
          "glucose": 311.0
        },
        {
          "timestamp": "2025-08-02T17:10:00+00:00",
          "glucose": 300.0
        },
        {
          "timestamp": "2025-08-02T17:15:00+00:00",
          "glucose": 288.0
        },
        {
          "timestamp": "2025-08-02T17:20:00+00:00",
          "glucose": 304.0
        },
        {
          "timestamp": "2025-08-02T17:25:00+00:00",
          "glucose": 290.0
        },
        {
          "timestamp": "2025-08-02T17:30:00+00:00",
          "glucose": 279.0
        },
        {
          "timestamp": "2025-08-02T17:35:00+00:00",
          "glucose": 262.0
        },
        {
          "timestamp": "2025-08-02T17:40:00+00:00",
          "glucose": 262.0
        },
        {
          "timestamp": "2025-08-02T17:45:00+00:00",
          "glucose": 265.0
        },
        {
          "timestamp": "2025-08-02T17:50:00+00:00",
          "glucose": 251.0
        },
        {
          "timestamp": "2025-08-02T17:55:00+00:00",
          "glucose": 257.0
        },
        {
          "timestamp": "2025-08-02T18:00:00+00:00",
          "glucose": 250.0
        },
        {
          "timestamp": "2025-08-02T18:05:00+00:00",
          "glucose": 257.0
        },
        {
          "timestamp": "2025-08-02T18:10:00+00:00",
          "glucose": 273.0
        },
        {
          "timestamp": "2025-08-02T18:15:00+00:00",
          "glucose": 289.0
        },
        {
          "timestamp": "2025-08-02T18:20:00+00:00",
          "glucose": 283.0
        },
        {
          "timestamp": "2025-08-02T18:25:00+00:00",
          "glucose": 284.0
        },
        {
          "timestamp": "2025-08-02T18:30:00+00:00",
          "glucose": 280.0
        },
        {
          "timestamp": "2025-08-02T18:35:00+00:00",
          "glucose": 275.0
        },
        {
          "timestamp": "2025-08-02T18:40:00+00:00",
          "glucose": 294.0
        },
        {
          "timestamp": "2025-08-02T18:45:00+00:00",
          "glucose": 298.0
        },
        {
          "timestamp": "2025-08-02T18:50:00+00:00",
          "glucose": 314.0
        },
        {
          "timestamp": "2025-08-02T18:55:00+00:00",
          "glucose": 322.0
        },
        {
          "timestamp": "2025-08-02T19:00:00+00:00",
          "glucose": 329.0
        },
        {
          "timestamp": "2025-08-02T19:05:00+00:00",
          "glucose": 343.0
        },
        {
          "timestamp": "2025-08-02T19:10:00+00:00",
          "glucose": 351.0
        },
        {
          "timestamp": "2025-08-02T19:15:00+00:00",
          "glucose": 334.0
        },
        {
          "timestamp": "2025-08-02T19:20:00+00:00",
          "glucose": 324.0
        },
        {
          "timestamp": "2025-08-02T19:25:00+00:00",
          "glucose": 333.0
        },
        {
          "timestamp": "2025-08-02T19:30:00+00:00",
          "glucose": 346.0
        },
        {
          "timestamp": "2025-08-02T19:35:00+00:00",
          "glucose": 343.0
        },
        {
          "timestamp": "2025-08-02T19:40:00+00:00",
          "glucose": 334.0
        },
        {
          "timestamp": "2025-08-02T19:45:00+00:00",
          "glucose": 326.0
        },
        {
          "timestamp": "2025-08-02T19:50:00+00:00",
          "glucose": 339.0
        },
        {
          "timestamp": "2025-08-02T19:55:00+00:00",
          "glucose": 320.0
        },
        {
          "timestamp": "2025-08-02T20:00:00+00:00",
          "glucose": 310.0
        },
        {
          "timestamp": "2025-08-02T20:05:00+00:00",
          "glucose": 305.0
        },
        {
          "timestamp": "2025-08-02T20:10:00+00:00",
          "glucose": 289.0
        },
        {
          "timestamp": "2025-08-02T20:15:00+00:00",
          "glucose": 307.0
        },
        {
          "timestamp": "2025-08-02T20:20:00+00:00",
          "glucose": 321.0
        },
        {
          "timestamp": "2025-08-02T20:25:00+00:00",
          "glucose": 304.0
        },
        {
          "timestamp": "2025-08-02T20:30:00+00:00",
          "glucose": 290.0
        },
        {
          "timestamp": "2025-08-02T20:35:00+00:00",
          "glucose": 285.0
        },
        {
          "timestamp": "2025-08-02T20:40:00+00:00",
          "glucose": 269.0
        },
        {
          "timestamp": "2025-08-02T20:45:00+00:00",
          "glucose": 251.0
        },
        {
          "timestamp": "2025-08-02T20:50:00+00:00",
          "glucose": 242.0
        },
        {
          "timestamp": "2025-08-02T20:55:00+00:00",
          "glucose": 257.0
        },
        {
          "timestamp": "2025-08-02T21:00:00+00:00",
          "glucose": 248.0
        },
        {
          "timestamp": "2025-08-02T21:05:00+00:00",
          "glucose": 241.0
        },
        {
          "timestamp": "2025-08-02T21:10:00+00:00",
          "glucose": 248.0
        },
        {
          "timestamp": "2025-08-02T21:15:00+00:00",
          "glucose": 237.0
        },
        {
          "timestamp": "2025-08-02T21:20:00+00:00",
          "glucose": 232.0
        },
        {
          "timestamp": "2025-08-02T21:25:00+00:00",
          "glucose": 244.0
        },
        {
          "timestamp": "2025-08-02T21:30:00+00:00",
          "glucose": 224.0
        },
        {
          "timestamp": "2025-08-02T21:35:00+00:00",
          "glucose": 206.0
        },
        {
          "timestamp": "2025-08-02T21:40:00+00:00",
          "glucose": 194.0
        },
        {
          "timestamp": "2025-08-02T21:45:00+00:00",
          "glucose": 185.0
        },
        {
          "timestamp": "2025-08-02T21:50:00+00:00",
          "glucose": 201.0
        },
        {
          "timestamp": "2025-08-02T21:55:00+00:00",
          "glucose": 194.0
        },
        {
          "timestamp": "2025-08-02T22:05:00+00:00",
          "glucose": 192.0
        },
        {
          "timestamp": "2025-08-02T22:10:00+00:00",
          "glucose": 192.0
        },
        {
          "timestamp": "2025-08-02T22:15:00+00:00",
          "glucose": 194.0
        },
        {
          "timestamp": "2025-08-02T22:20:00+00:00",
          "glucose": 185.0
        },
        {
          "timestamp": "2025-08-02T22:35:00+00:00",
          "glucose": 182.0
        },
        {
          "timestamp": "2025-08-02T22:40:00+00:00",
          "glucose": 193.0
        },
        {
          "timestamp": "2025-08-02T22:45:00+00:00",
          "glucose": 198.0
        },
        {
          "timestamp": "2025-08-02T22:50:00+00:00",
          "glucose": 192.0
        },
        {
          "timestamp": "2025-08-02T22:55:00+00:00",
          "glucose": 199.0
        },
        {
          "timestamp": "2025-08-02T23:05:00+00:00",
          "glucose": 200.0
        },
        {
          "timestamp": "2025-08-02T23:10:00+00:00",
          "glucose": 197.0
        },
        {
          "timestamp": "2025-08-02T23:15:00+00:00",
          "glucose": 201.0
        },
        {
          "timestamp": "2025-08-02T23:20:00+00:00",
          "glucose": 221.0
        },
        {
          "timestamp": "2025-08-02T23:25:00+00:00",
          "glucose": 215.0
        },
        {
          "timestamp": "2025-08-02T23:30:00+00:00",
          "glucose": 207.0
        },
        {
          "timestamp": "2025-08-02T23:35:00+00:00",
          "glucose": 199.0
        },
        {
          "timestamp": "2025-08-02T23:40:00+00:00",
          "glucose": 204.0
        },
        {
          "timestamp": "2025-08-02T23:45:00+00:00",
          "glucose": 221.0
        },
        {
          "timestamp": "2025-08-02T23:50:00+00:00",
          "glucose": 228.0
        },
        {
          "timestamp": "2025-08-02T23:55:00+00:00",
          "glucose": 247.0
        },
        {
          "timestamp": "2025-08-03T08:00:00+00:00",
          "glucose": 335.0
        },
        {
          "timestamp": "2025-08-03T08:05:00+00:00",
          "glucose": 337.0
        },
        {
          "timestamp": "2025-08-03T08:10:00+00:00",
          "glucose": 345.0
        },
        {
          "timestamp": "2025-08-03T08:15:00+00:00",
          "glucose": 339.0
        },
        {
          "timestamp": "2025-08-03T08:20:00+00:00",
          "glucose": 357.0
        },
        {
          "timestamp": "2025-08-03T08:25:00+00:00",
          "glucose": 338.0
        },
        {
          "timestamp": "2025-08-03T08:30:00+00:00",
          "glucose": 354.0
        },
        {
          "timestamp": "2025-08-03T08:35:00+00:00",
          "glucose": 361.0
        },
        {
          "timestamp": "2025-08-03T08:40:00+00:00",
          "glucose": 353.0
        },
        {
          "timestamp": "2025-08-03T08:45:00+00:00",
          "glucose": 340.0
        },
        {
          "timestamp": "2025-08-03T08:50:00+00:00",
          "glucose": 323.0
        },
        {
          "timestamp": "2025-08-03T08:55:00+00:00",
          "glucose": 322.0
        },
        {
          "timestamp": "2025-08-03T09:00:00+00:00",
          "glucose": 338.0
        },
        {
          "timestamp": "2025-08-03T09:05:00+00:00",
          "glucose": 354.0
        },
        {
          "timestamp": "2025-08-03T09:10:00+00:00",
          "glucose": 358.0
        },
        {
          "timestamp": "2025-08-03T09:15:00+00:00",
          "glucose": 340.0
        },
        {
          "timestamp": "2025-08-03T09:20:00+00:00",
          "glucose": 325.0
        },
        {
          "timestamp": "2025-08-03T09:25:00+00:00",
          "glucose": 341.0
        },
        {
          "timestamp": "2025-08-03T09:30:00+00:00",
          "glucose": 325.0
        },
        {
          "timestamp": "2025-08-03T09:35:00+00:00",
          "glucose": 342.0
        },
        {
          "timestamp": "2025-08-03T09:40:00+00:00",
          "glucose": 329.0
        },
        {
          "timestamp": "2025-08-03T09:45:00+00:00",
          "glucose": 348.0
        },
        {
          "timestamp": "2025-08-03T09:50:00+00:00",
          "glucose": 330.0
        },
        {
          "timestamp": "2025-08-03T09:55:00+00:00",
          "glucose": 336.0
        },
        {
          "timestamp": "2025-08-03T10:00:00+00:00",
          "glucose": 352.0
        },
        {
          "timestamp": "2025-08-03T10:05:00+00:00",
          "glucose": 354.0
        },
        {
          "timestamp": "2025-08-03T10:10:00+00:00",
          "glucose": 337.0
        },
        {
          "timestamp": "2025-08-03T10:15:00+00:00",
          "glucose": 339.0
        },
        {
          "timestamp": "2025-08-03T10:20:00+00:00",
          "glucose": 349.0
        },
        {
          "timestamp": "2025-08-03T10:25:00+00:00",
          "glucose": 343.0
        },
        {
          "timestamp": "2025-08-03T10:30:00+00:00",
          "glucose": 328.0
        },
        {
          "timestamp": "2025-08-03T10:35:00+00:00",
          "glucose": 344.0
        },
        {
          "timestamp": "2025-08-03T10:40:00+00:00",
          "glucose": 330.0
        },
        {
          "timestamp": "2025-08-03T10:45:00+00:00",
          "glucose": 322.0
        },
        {
          "timestamp": "2025-08-03T10:50:00+00:00",
          "glucose": 324.0
        },
        {
          "timestamp": "2025-08-03T10:55:00+00:00",
          "glucose": 310.0
        },
        {
          "timestamp": "2025-08-03T11:00:00+00:00",
          "glucose": 302.0
        },
        {
          "timestamp": "2025-08-03T11:05:00+00:00",
          "glucose": 296.0
        },
        {
          "timestamp": "2025-08-03T11:10:00+00:00",
          "glucose": 312.0
        },
        {
          "timestamp": "2025-08-03T11:15:00+00:00",
          "glucose": 306.0
        },
        {
          "timestamp": "2025-08-03T11:20:00+00:00",
          "glucose": 321.0
        },
        {
          "timestamp": "2025-08-03T11:25:00+00:00",
          "glucose": 321.0
        },
        {
          "timestamp": "2025-08-03T11:30:00+00:00",
          "glucose": 338.0
        },
        {
          "timestamp": "2025-08-03T11:35:00+00:00",
          "glucose": 341.0
        },
        {
          "timestamp": "2025-08-03T11:40:00+00:00",
          "glucose": 346.0
        },
        {
          "timestamp": "2025-08-03T11:45:00+00:00",
          "glucose": 334.0
        },
        {
          "timestamp": "2025-08-03T11:50:00+00:00",
          "glucose": 354.0
        },
        {
          "timestamp": "2025-08-03T11:55:00+00:00",
          "glucose": 353.0
        },
        {
          "timestamp": "2025-08-03T12:00:00+00:00",
          "glucose": 335.0
        },
        {
          "timestamp": "2025-08-03T12:05:00+00:00",
          "glucose": 342.0
        },
        {
          "timestamp": "2025-08-03T12:10:00+00:00",
          "glucose": 348.0
        },
        {
          "timestamp": "2025-08-03T12:15:00+00:00",
          "glucose": 360.0
        },
        {
          "timestamp": "2025-08-03T12:20:00+00:00",
          "glucose": 352.0
        },
        {
          "timestamp": "2025-08-03T12:25:00+00:00",
          "glucose": 335.0
        },
        {
          "timestamp": "2025-08-03T12:30:00+00:00",
          "glucose": 332.0
        },
        {
          "timestamp": "2025-08-03T12:35:00+00:00",
          "glucose": 338.0
        },
        {
          "timestamp": "2025-08-03T12:40:00+00:00",
          "glucose": 350.0
        },
        {
          "timestamp": "2025-08-03T12:45:00+00:00",
          "glucose": 365.0
        },
        {
          "timestamp": "2025-08-03T12:50:00+00:00",
          "glucose": 365.0
        },
        {
          "timestamp": "2025-08-03T12:55:00+00:00",
          "glucose": 363.0
        },
        {
          "timestamp": "2025-08-03T13:00:00+00:00",
          "glucose": 350.0
        },
        {
          "timestamp": "2025-08-03T13:05:00+00:00",
          "glucose": 348.0
        },
        {
          "timestamp": "2025-08-03T13:10:00+00:00",
          "glucose": 328.0
        },
        {
          "timestamp": "2025-08-03T13:15:00+00:00",
          "glucose": 315.0
        },
        {
          "timestamp": "2025-08-03T13:20:00+00:00",
          "glucose": 329.0
        },
        {
          "timestamp": "2025-08-03T13:25:00+00:00",
          "glucose": 318.0
        },
        {
          "timestamp": "2025-08-03T13:30:00+00:00",
          "glucose": 330.0
        },
        {
          "timestamp": "2025-08-03T13:35:00+00:00",
          "glucose": 310.0
        },
        {
          "timestamp": "2025-08-03T13:40:00+00:00",
          "glucose": 303.0
        },
        {
          "timestamp": "2025-08-03T13:45:00+00:00",
          "glucose": 284.0
        },
        {
          "timestamp": "2025-08-03T13:50:00+00:00",
          "glucose": 268.0
        },
        {
          "timestamp": "2025-08-03T13:55:00+00:00",
          "glucose": 276.0
        },
        {
          "timestamp": "2025-08-03T14:00:00+00:00",
          "glucose": 291.0
        },
        {
          "timestamp": "2025-08-03T14:05:00+00:00",
          "glucose": 293.0
        },
        {
          "timestamp": "2025-08-03T14:10:00+00:00",
          "glucose": 273.0
        },
        {
          "timestamp": "2025-08-03T14:15:00+00:00",
          "glucose": 262.0
        },
        {
          "timestamp": "2025-08-03T14:20:00+00:00",
          "glucose": 248.0
        },
        {
          "timestamp": "2025-08-03T14:25:00+00:00",
          "glucose": 262.0
        },
        {
          "timestamp": "2025-08-03T14:30:00+00:00",
          "glucose": 243.0
        },
        {
          "timestamp": "2025-08-03T14:35:00+00:00",
          "glucose": 229.0
        },
        {
          "timestamp": "2025-08-03T14:40:00+00:00",
          "glucose": 210.0
        },
        {
          "timestamp": "2025-08-03T14:45:00+00:00",
          "glucose": 190.0
        },
        {
          "timestamp": "2025-08-03T14:50:00+00:00",
          "glucose": 206.0
        },
        {
          "timestamp": "2025-08-03T14:55:00+00:00",
          "glucose": 190.0
        },
        {
          "timestamp": "2025-08-03T15:25:00+00:00",
          "glucose": 187.0
        },
        {
          "timestamp": "2025-08-03T15:35:00+00:00",
          "glucose": 194.0
        },
        {
          "timestamp": "2025-08-03T16:00:00+00:00",
          "glucose": 320.0
        },
        {
          "timestamp": "2025-08-03T16:05:00+00:00",
          "glucose": 307.0
        },
        {
          "timestamp": "2025-08-03T16:10:00+00:00",
          "glucose": 322.0
        },
        {
          "timestamp": "2025-08-03T16:15:00+00:00",
          "glucose": 340.0
        },
        {
          "timestamp": "2025-08-03T16:20:00+00:00",
          "glucose": 345.0
        },
        {
          "timestamp": "2025-08-03T16:25:00+00:00",
          "glucose": 330.0
        },
        {
          "timestamp": "2025-08-03T16:30:00+00:00",
          "glucose": 311.0
        },
        {
          "timestamp": "2025-08-03T16:35:00+00:00",
          "glucose": 301.0
        },
        {
          "timestamp": "2025-08-03T16:40:00+00:00",
          "glucose": 312.0
        },
        {
          "timestamp": "2025-08-03T16:45:00+00:00",
          "glucose": 327.0
        },
        {
          "timestamp": "2025-08-03T16:50:00+00:00",
          "glucose": 334.0
        },
        {
          "timestamp": "2025-08-03T16:55:00+00:00",
          "glucose": 353.0
        },
        {
          "timestamp": "2025-08-03T17:00:00+00:00",
          "glucose": 341.0
        },
        {
          "timestamp": "2025-08-03T17:05:00+00:00",
          "glucose": 360.0
        },
        {
          "timestamp": "2025-08-03T17:10:00+00:00",
          "glucose": 343.0
        },
        {
          "timestamp": "2025-08-03T17:15:00+00:00",
          "glucose": 354.0
        },
        {
          "timestamp": "2025-08-03T17:20:00+00:00",
          "glucose": 360.0
        },
        {
          "timestamp": "2025-08-03T17:25:00+00:00",
          "glucose": 379.0
        },
        {
          "timestamp": "2025-08-03T17:30:00+00:00",
          "glucose": 392.0
        },
        {
          "timestamp": "2025-08-03T17:35:00+00:00",
          "glucose": 408.0
        },
        {
          "timestamp": "2025-08-03T17:40:00+00:00",
          "glucose": 400.0
        },
        {
          "timestamp": "2025-08-03T17:45:00+00:00",
          "glucose": 405.0
        },
        {
          "timestamp": "2025-08-03T17:50:00+00:00",
          "glucose": 400.0
        },
        {
          "timestamp": "2025-08-03T17:55:00+00:00",
          "glucose": 395.0
        },
        {
          "timestamp": "2025-08-03T18:00:00+00:00",
          "glucose": 390.0
        },
        {
          "timestamp": "2025-08-03T18:05:00+00:00",
          "glucose": 378.0
        },
        {
          "timestamp": "2025-08-03T18:10:00+00:00",
          "glucose": 393.0
        },
        {
          "timestamp": "2025-08-03T18:15:00+00:00",
          "glucose": 373.0
        },
        {
          "timestamp": "2025-08-03T18:20:00+00:00",
          "glucose": 354.0
        },
        {
          "timestamp": "2025-08-03T18:25:00+00:00",
          "glucose": 373.0
        },
        {
          "timestamp": "2025-08-03T18:30:00+00:00",
          "glucose": 386.0
        },
        {
          "timestamp": "2025-08-03T18:35:00+00:00",
          "glucose": 383.0
        },
        {
          "timestamp": "2025-08-03T18:40:00+00:00",
          "glucose": 375.0
        },
        {
          "timestamp": "2025-08-03T18:45:00+00:00",
          "glucose": 390.0
        },
        {
          "timestamp": "2025-08-03T18:50:00+00:00",
          "glucose": 397.0
        },
        {
          "timestamp": "2025-08-03T18:55:00+00:00",
          "glucose": 391.0
        },
        {
          "timestamp": "2025-08-03T19:00:00+00:00",
          "glucose": 396.0
        },
        {
          "timestamp": "2025-08-03T19:05:00+00:00",
          "glucose": 382.0
        },
        {
          "timestamp": "2025-08-03T19:10:00+00:00",
          "glucose": 367.0
        },
        {
          "timestamp": "2025-08-03T19:15:00+00:00",
          "glucose": 387.0
        },
        {
          "timestamp": "2025-08-03T19:20:00+00:00",
          "glucose": 390.0
        },
        {
          "timestamp": "2025-08-03T19:25:00+00:00",
          "glucose": 370.0
        },
        {
          "timestamp": "2025-08-03T19:30:00+00:00",
          "glucose": 379.0
        },
        {
          "timestamp": "2025-08-03T19:35:00+00:00",
          "glucose": 365.0
        },
        {
          "timestamp": "2025-08-03T19:40:00+00:00",
          "glucose": 351.0
        },
        {
          "timestamp": "2025-08-03T19:45:00+00:00",
          "glucose": 349.0
        },
        {
          "timestamp": "2025-08-03T19:50:00+00:00",
          "glucose": 337.0
        },
        {
          "timestamp": "2025-08-03T19:55:00+00:00",
          "glucose": 324.0
        },
        {
          "timestamp": "2025-08-03T20:00:00+00:00",
          "glucose": 305.0
        },
        {
          "timestamp": "2025-08-03T20:05:00+00:00",
          "glucose": 308.0
        },
        {
          "timestamp": "2025-08-03T20:10:00+00:00",
          "glucose": 319.0
        },
        {
          "timestamp": "2025-08-03T20:15:00+00:00",
          "glucose": 305.0
        },
        {
          "timestamp": "2025-08-03T20:20:00+00:00",
          "glucose": 302.0
        },
        {
          "timestamp": "2025-08-03T20:25:00+00:00",
          "glucose": 284.0
        },
        {
          "timestamp": "2025-08-03T20:30:00+00:00",
          "glucose": 277.0
        },
        {
          "timestamp": "2025-08-03T20:35:00+00:00",
          "glucose": 283.0
        },
        {
          "timestamp": "2025-08-03T20:40:00+00:00",
          "glucose": 263.0
        },
        {
          "timestamp": "2025-08-03T20:45:00+00:00",
          "glucose": 243.0
        },
        {
          "timestamp": "2025-08-03T20:50:00+00:00",
          "glucose": 234.0
        },
        {
          "timestamp": "2025-08-03T20:55:00+00:00",
          "glucose": 230.0
        },
        {
          "timestamp": "2025-08-03T21:00:00+00:00",
          "glucose": 210.0
        },
        {
          "timestamp": "2025-08-03T21:05:00+00:00",
          "glucose": 210.0
        },
        {
          "timestamp": "2025-08-03T21:10:00+00:00",
          "glucose": 191.0
        }
      ],
      "postprandial_spikes": [
        {
          "start": "2025-08-01T06:20:00+00:00",
          "end": "2025-08-01T07:20:00+00:00",
          "delta": 47.0
        },
        {
          "start": "2025-08-01T08:40:00+00:00",
          "end": "2025-08-01T09:40:00+00:00",
          "delta": 52.0
        },
        {
          "start": "2025-08-01T09:00:00+00:00",
          "end": "2025-08-01T10:00:00+00:00",
          "delta": 89.0
        },
        {
          "start": "2025-08-01T12:00:00+00:00",
          "end": "2025-08-01T13:00:00+00:00",
          "delta": 46.0
        },
        {
          "start": "2025-08-01T13:00:00+00:00",
          "end": "2025-08-01T14:00:00+00:00",
          "delta": 52.0
        },
        {
          "start": "2025-08-01T14:05:00+00:00",
          "end": "2025-08-01T15:05:00+00:00",
          "delta": 41.0
        },
        {
          "start": "2025-08-01T15:00:00+00:00",
          "end": "2025-08-01T16:00:00+00:00",
          "delta": 182.0
        },
        {
          "start": "2025-08-01T20:45:00+00:00",
          "end": "2025-08-01T21:45:00+00:00",
          "delta": 51.0
        },
        {
          "start": "2025-08-01T21:00:00+00:00",
          "end": "2025-08-01T22:00:00+00:00",
          "delta": 57.0
        },
        {
          "start": "2025-08-02T09:35:00+00:00",
          "end": "2025-08-02T10:35:00+00:00",
          "delta": 41.0
        },
        {
          "start": "2025-08-02T12:30:00+00:00",
          "end": "2025-08-02T13:30:00+00:00",
          "delta": 44.0
        },
        {
          "start": "2025-08-02T13:40:00+00:00",
          "end": "2025-08-02T14:40:00+00:00",
          "delta": 46.0
        },
        {
          "start": "2025-08-02T14:00:00+00:00",
          "end": "2025-08-02T15:00:00+00:00",
          "delta": 123.0
        },
        {
          "start": "2025-08-02T15:00:00+00:00",
          "end": "2025-08-02T16:00:00+00:00",
          "delta": 170.0
        },
        {
          "start": "2025-08-02T17:50:00+00:00",
          "end": "2025-08-02T18:50:00+00:00",
          "delta": 63.0
        },
        {
          "start": "2025-08-02T18:00:00+00:00",
          "end": "2025-08-02T19:00:00+00:00",
          "delta": 79.0
        },
        {
          "start": "2025-08-02T22:25:00+00:00",
          "end": "2025-08-02T23:25:00+00:00",
          "delta": 45.0
        },
        {
          "start": "2025-08-03T06:25:00+00:00",
          "end": "2025-08-03T07:25:00+00:00",
          "delta": 42.0
        },
        {
          "start": "2025-08-03T07:00:00+00:00",
          "end": "2025-08-03T08:00:00+00:00",
          "delta": 290.0
        },
        {
          "start": "2025-08-03T10:55:00+00:00",
          "end": "2025-08-03T11:55:00+00:00",
          "delta": 43.0
        },
        {
          "start": "2025-08-03T11:05:00+00:00",
          "end": "2025-08-03T12:05:00+00:00",
          "delta": 46.0
        },
        {
          "start": "2025-08-03T15:00:00+00:00",
          "end": "2025-08-03T16:00:00+00:00",
          "delta": 149.0
        },
        {
          "start": "2025-08-03T16:05:00+00:00",
          "end": "2025-08-03T17:05:00+00:00",
          "delta": 53.0
        },
        {
          "start": "2025-08-03T17:00:00+00:00",
          "end": "2025-08-03T18:00:00+00:00",
          "delta": 49.0
        }
      ],
      "dawn_phenomenon": true
    },
    "recommendation_context": {
      "high_cv": true,
      "low_tir": true,
      "frequent_hypos": true,
      "frequent_spikes": true,
      "dawn_present": true
    }
  },
  "interpretation_text": "The patient\u2019s CGM data demonstrate suboptimal glycemic control, with a markedly elevated mean glucose of 208 mg/dL (GMI 8.29%) and significant glycemic variability (SD 121.5 mg/dL, CV 58.4%). Time in range is low at 21.1%, with excessive time spent both above (56.8%) and below (22.1%) target glucose levels. There is a high frequency of hypoglycemia events (191 total, 66 nocturnal) and hyperglycemia events (491), with evidence of the dawn phenomenon and 24 postprandial spikes.\n\nAbnormal patterns include frequent and significant nocturnal hypoglycemia, recurrent postprandial hyperglycemic excursions, and pronounced dawn phenomenon, all contributing to high glycemic variability.\n\nRecommendations: Intensify glucose control to increase time in range and reduce both hypo- and hyperglycemia. Reassess overnight basal insulin dosing to minimize nocturnal hypoglycemia. Review the patient\u2019s hypoglycemia awareness and carbohydrate intake. Address elevated glycemic variability by optimizing basal-bolus dosing and meal timing. Investigate causes of postprandial spikes, including possible missed boluses or carbohydrate misestimation. Adjust basal insulin regimen or consider split dosing to address the dawn phenomenon."
}